{"player": {"x": 4, "y": 23, "step": 1, "is_active": true, "max_x": 30, "max_y": 25, "speed": 1.0999999999999999, "hp": 7, "water": 1, "hp_capacity": 9, "water_capacity": 11}, "hospital": {"x": 2, "y": 2, "step": 0, "is_active": true, "max_x": 30, "max_y": 25}, "workshop": {"x": 4, "y": 2, "step": 0, "is_active": true, "max_x": 30, "max_y": 25}, "game_handler": {"clouds_list": [{"x": 2, "y": 1, "step": 1, "is_active": true, "max_x": 30, "max_y": 25}, {"x": 5, "y": 12, "step": 1, "is_active": true, "max_x": 30, "max_y": 25}, {"x": 8, "y": 17, "step": 1, "is_active": true, "max_x": 30, "max_y": 25}, {"x": 11, "y": 3, "step": 1, "is_active": true, "max_x": 30, "max_y": 25}, {"x": 14, "y": 10, "step": 1, "is_active": true, "max_x": 30, "max_y": 25}, {"x": 17, "y": 1, "step": 1, "is_active": true, "max_x": 30, "max_y": 25}, {"x": 20, "y": 3, "step": 1, "is_active": true, "max_x": 30, "max_y": 25}, {"x": 23, "y": 22, "step": 1, "is_active": true, "max_x": 30, "max_y": 25}, {"x": 26, "y": 14, "step": 1, "is_active": true, "max_x": 30, "max_y": 25}], "fire_list": [[17, 15, 3404], [20, 9, 3814], [3, 6, 4657], [8, 23, 5291], [5, 5, 5208]], "max_fire_len_list": 20, "fire_count_coef": 0.5, "water_density": 0.01, "forest_density": 30, "score": 3396.5625}, "game_map": {"size_x": 30, "size_y": 25, "cash_map_matrix": [["\ud83d\udfeb", "\ud83d\udfeb", "\ud83d\udfeb", "\ud83d\udfeb", "\ud83d\udfeb", "\ud83d\udfeb", "\ud83d\udfeb", "\ud83d\udfeb", "\ud83d\udfeb", "\ud83d\udfeb", "\ud83d\udfeb", "\ud83d\udfeb", "\ud83d\udfeb", "\ud83d\udfeb", "\ud83d\udfeb", "\ud83d\udfeb", "\ud83d\udfeb", "\ud83d\udfeb", "\ud83d\udfeb", "\ud83d\udfeb", "\ud83d\udfeb", "\ud83d\udfeb", "\ud83d\udfeb", "\ud83d\udfeb", "\ud83d\udfeb", "\ud83d\udfeb", "\ud83d\udfeb", "\ud83d\udfeb", "\ud83d\udfeb", "\ud83d\udfeb"], ["\ud83d\udfeb", "\ud83d\udfe9", "\ud83d\udfe9", "\ud83d\udfe9", "\ud83d\udfe9", "\ud83d\udfe9", "\ud83d\udfe9", "\ud83c\udf32", "\ud83c\udf32", "\ud83d\udfe9", "\ud83c\udf32", "\ud83c\udf32", "\ud83c\udf32", "\ud83c\udf32", "\ud83c\udf32", "\ud83d\udfe9", "\ud83d\udfe9", "\ud83c\udf32", "\ud83c\udf32", "\ud83c\udf32", "\ud83d\udfe9", "\ud83d\udfe9", "\ud83c\udf32", "\ud83d\udfe9", "\ud83c\udf32", "\ud83c\udf32", "\ud83d\udfe9", "\ud83d\udfe9", "\ud83d\udfe9", "\ud83d\udfeb"], ["\ud83d\udfeb", "\ud83d\udfe9", "\ud83d\udfe9", "\ud83c\udf32", "\ud83d\udfe9", "\ud83d\udfe9", "\ud83d\udfe9", "\ud83d\udfe9", "\ud83d\udfe9", "\ud83d\udfe9", "\ud83c\udf32", "\ud83d\udfe9", "\ud83d\udfe9", "\ud83d\udfe9", "\ud83d\udfe9", "\ud83d\udfe9", "\ud83d\udfe9", "\ud83d\udfe9", "\ud83d\udfe9", "\ud83d\udfe9", "\ud83d\udfe9", "\ud83d\udfe9", "\ud83c\udf32", "\ud83d\udfe9", "\ud83d\udfe9", "\ud83d\udfe9", "\ud83d\udfe9", "\ud83d\udfe9", "\ud83d\udfe9", "\ud83d\udfeb"], ["\ud83d\udfeb", "\ud83d\udfe9", "\ud83d\udfe9", "\ud83c\udf32", "\ud83d\udfe9", "\ud83c\udf32", "\ud83d\udfe9", "\ud83c\udf32", "\ud83d\udfe9", "\ud83d\udfe9", "\ud83c\udf32", "\ud83c\udf32", "\ud83d\udfe9", "\ud83d\udfe9", "\ud83d\udfe9", "\ud83d\udfe9", "\ud83d\udfe9", "\ud83d\udfe9", "\ud83d\udfe9", "\ud83d\udfe9", "\ud83d\udfe9", "\ud83d\udfe9", "\ud83d\udfe9", "\ud83d\udfe9", "\ud83d\udfe9", "\ud83d\udfe9", "\ud83d\udfe9", "\ud83d\udfe9", "\ud83d\udfe9", "\ud83d\udfeb"], ["\ud83d\udfeb", "\ud83d\udfe9", "\ud83c\udf32", "\ud83d\udfe9", "\ud83d\udfe9", "\ud83c\udf32", "\ud83d\udfe9", "\ud83d\udfe9", "\ud83d\udfe9", "\ud83d\udfe9", "\ud83c\udf32", "\ud83d\udfe9", "\ud83d\udfe9", "\ud83d\udfe9", "\ud83d\udfe9", "\ud83d\udfe9", "\ud83d\udfe9", "\ud83c\udf32", "\ud83d\udfe9", "\ud83d\udfe9", "\ud83d\udfe9", "\ud83d\udfe9", "\ud83d\udfe9", "\ud83d\udfe9", "\ud83c\udf32", "\ud83d\udfe9", "\ud83d\udfe9", "\ud83d\udfe9", "\ud83d\udfe9", "\ud83d\udfeb"], ["\ud83d\udfeb", "\ud83d\udfe9", "\ud83d\udfe9", "\ud83d\udfe9", "\ud83c\udf32", "\ud83d\udd25", "\ud83d\udfe9", "\ud83c\udf32", "\ud83c\udf32", "\ud83d\udfe9", "\ud83c\udf32", "\ud83d\udfe9", "\ud83d\udfe9", "\ud83d\udfe9", "\ud83c\udf32", "\ud83c\udf32", "\ud83c\udf32", "\ud83d\udfe9", "\ud83d\udfe9", "\ud83d\udfe9", "\ud83d\udfe9", "\ud83c\udf32", "\ud83d\udfe9", "\ud83c\udf32", "\ud83d\udfe9", "\ud83c\udf32", "\ud83d\udfe9", "\ud83d\udfe9", "\ud83d\udfe9", "\ud83d\udfeb"], ["\ud83d\udfeb", "\ud83d\udfe9", "\ud83d\udfe9", "\ud83d\udd25", "\ud83d\udfe9", "\ud83c\udf32", "\ud83c\udf32", "\ud83d\udfe9", "\ud83d\udfe9", "\ud83d\udfe9", "\ud83c\udf32", "\ud83d\udfe9", "\ud83c\udf32", "\ud83d\udfe9", "\ud83c\udf32", "\ud83d\udfe9", "\ud83c\udf32", "\ud83d\udfe9", "\ud83d\udfe9", "\ud83d\udfe9", "\ud83d\udfe9", "\ud83d\udfe9", "\ud83c\udf32", "\ud83c\udf32", "\ud83c\udf32", "\ud83d\udfe9", "\ud83c\udf32", "\ud83d\udfe9", "\ud83d\udfe9", "\ud83d\udfeb"], ["\ud83d\udfeb", "\ud83d\udfe9", "\ud83d\udfe9", "\ud83c\udf32", "\ud83d\udfe9", "\ud83d\udfe9", "\ud83c\udf32", "\ud83c\udf32", "\ud83d\udfe9", "\ud83c\udf32", "\ud83c\udf32", "\ud83c\udf32", "\ud83c\udf32", "\ud83d\udfe9", "\ud83c\udf32", "\ud83d\udfe9", "\ud83d\udfe9", "\ud83d\udfe9", "\ud83d\udfe9", "\ud83d\udfe9", "\ud83d\udfe9", "\ud83c\udf32", "\ud83d\udfe9", "\ud83d\udfe9", "\ud83d\udfe9", "\ud83d\udfe9", "\ud83d\udfe9", "\ud83d\udfe9", "\ud83d\udfe9", "\ud83d\udfeb"], ["\ud83d\udfeb", "\ud83d\udfe9", "\ud83d\udfe9", "\ud83d\udfe9", "\ud83d\udfe9", "\ud83d\udfe9", "\ud83c\udf32", "\ud83d\udfe9", "\ud83d\udfe9", "\ud83c\udf32", "\ud83d\udfe9", "\ud83d\udfe9", "\ud83d\udfe9", "\ud83d\udfe9", "\ud83d\udfe9", "\ud83d\udfe9", "\ud83d\udfe9", "\ud83d\udfe9", "\ud83d\udfe9", "\ud83d\udfe9", "\ud83c\udf32", "\ud83d\udfe9", "\ud83d\udfe9", "\ud83d\udfe9", "\ud83c\udf32", "\ud83d\udfe9", "\ud83d\udfe9", "\ud83d\udfe9", "\ud83d\udfe9", "\ud83d\udfeb"], ["\ud83d\udfeb", "\ud83d\udfe9", "\ud83d\udfe9", "\ud83d\udfe9", "\ud83d\udfe9", "\ud83c\udf32", "\ud83d\udfe9", "\ud83c\udf32", "\ud83c\udf32", "\ud83c\udf32", "\ud83c\udf32", "\ud83c\udf32", "\ud83d\udfe9", "\ud83d\udfe9", "\ud83d\udfe9", "\ud83d\udfe9", "\ud83d\udfe9", "\ud83d\udfe9", "\ud83d\udfe9", "\ud83c\udf32", "\ud83d\udd25", "\ud83d\udfe9", "\ud83d\udfe9", "\ud83c\udf32", "\ud83c\udf32", "\ud83c\udf32", "\ud83d\udfe9", "\ud83d\udfe9", "\ud83d\udfe9", "\ud83d\udfeb"], ["\ud83d\udfeb", "\ud83d\udfe9", "\ud83c\udf32", "\ud83d\udfe9", "\ud83d\udfe9", "\ud83d\udfe9", "\ud83c\udf32", "\ud83c\udf32", "\ud83d\udfe9", "\ud83d\udfe9", "\ud83d\udfe9", "\ud83d\udfe9", "\ud83d\udfe9", "\ud83d\udfe9", "\ud83d\udfe9", "\ud83d\udfe9", "\ud83d\udfe9", "\ud83d\udfe9", "\ud83d\udfe9", "\ud83d\udfe9", "\ud83d\udfe9", "\ud83d\udfe9", "\ud83d\udfe9", "\ud83d\udfe9", "\ud83d\udfe9", "\ud83d\udfe9", "\ud83d\udfe9", "\ud83d\udfe9", "\ud83d\udfe9", "\ud83d\udfeb"], ["\ud83d\udfeb", "\ud83d\udfe9", "\ud83c\udf32", "\ud83d\udfe9", "\ud83d\udfe9", "\ud83c\udf32", "\ud83c\udf32", "\ud83c\udf32", "\ud83c\udf32", "\ud83d\udfe9", "\ud83d\udfe9", "\ud83d\udfe9", "\ud83d\udfe9", "\ud83d\udfe9", "\ud83d\udfe9", "\ud83d\udfe9", "\ud83d\udfe9", "\ud83d\udfe9", "\ud83c\udf32", "\ud83c\udf32", "\ud83d\udfe9", "\ud83d\udfe9", "\ud83d\udfe9", "\ud83d\udfe9", "\ud83d\udfe9", "\ud83d\udfe9", "\ud83d\udfe9", "\ud83d\udfe9", "\ud83d\udfe9", "\ud83d\udfeb"], ["\ud83d\udfeb", "\ud83c\udf32", "\ud83c\udf32", "\ud83c\udf32", "\ud83d\udfe9", "\ud83d\udfe9", "\ud83c\udf32", "\ud83d\udfe9", "\ud83d\udfe9", "\ud83d\udfe9", "\ud83d\udfe9", "\ud83d\udfe9", "\ud83d\udfe9", "\ud83d\udfe9", "\ud83d\udfe9", "\ud83d\udfe9", "\ud83d\udfe9", "\ud83d\udfe9", "\ud83d\udfe9", "\ud83c\udf32", "\ud83d\udfe9", "\ud83d\udfe9", "\ud83d\udfe9", "\ud83d\udfe9", "\ud83d\udfe9", "\ud83d\udfe9", "\ud83d\udfe9", "\ud83d\udfe9", "\ud83d\udfe9", "\ud83d\udfeb"], ["\ud83d\udfeb", "\ud83d\udfe9", "\ud83d\udfe9", "\ud83d\udfe9", "\ud83c\udf32", "\ud83d\udfe9", "\ud83c\udf32", "\ud83c\udf32", "\ud83d\udfe9", "\ud83d\udfe9", "\ud83c\udf32", "\ud83d\udfe9", "\ud83d\udfe9", "\ud83d\udfe9", "\ud83d\udfe9", "\ud83d\udfe9", "\ud83d\udfe9", "\ud83d\udfe9", "\ud83d\udfe9", "\ud83d\udfe9", "\ud83d\udfe9", "\ud83c\udf32", "\ud83d\udfe9", "\ud83d\udfe9", "\ud83d\udfe9", "\ud83d\udfe9", "\ud83d\udfe9", "\ud83d\udfe9", "\ud83d\udfe9", "\ud83d\udfeb"], ["\ud83d\udfeb", "\ud83d\udfe9", "\ud83d\udfe9", "\ud83c\udf32", "\ud83d\udfe9", "\ud83d\udfe9", "\ud83c\udf32", "\ud83d\udfe9", "\ud83c\udf32", "\ud83d\udfe9", "\ud83c\udf32", "\ud83d\udfe9", "\ud83d\udfe9", "\ud83d\udfe9", "\ud83d\udfe9", "\ud83d\udfe9", "\ud83c\udf32", "\ud83d\udfe9", "\ud83c\udf32", "\ud83d\udfe9", "\ud83d\udfe9", "\ud83d\udfe9", "\ud83d\udfe9", "\ud83d\udfe9", "\ud83d\udfe9", "\ud83d\udfe9", "\ud83d\udfe9", "\ud83d\udfe9", "\ud83d\udfe9", "\ud83d\udfeb"], ["\ud83d\udfeb", "\ud83d\udfe9", "\ud83d\udfe9", "\ud83c\udf32", "\ud83c\udf32", "\ud83c\udf32", "\ud83d\udfe9", "\ud83d\udfe9", "\ud83d\udfe9", "\ud83d\udfe9", "\ud83d\udfe9", "\ud83c\udf32", "\ud83c\udf32", "\ud83d\udfe9", "\ud83d\udfe9", "\ud83d\udfe9", "\ud83d\udfe9", "\ud83d\udd25", "\ud83c\udf32", "\ud83d\udfe9", "\ud83c\udf32", "\ud83d\udfe9", "\ud83d\udfe9", "\ud83d\udfe9", "\ud83d\udfe9", "\ud83d\udfe9", "\ud83d\udfe9", "\ud83d\udfe9", "\ud83d\udfe9", "\ud83d\udfeb"], ["\ud83d\udfeb", "\ud83c\udf32", "\ud83d\udfe9", "\ud83d\udfe9", "\ud83c\udf32", "\ud83c\udf32", "\ud83d\udfe9", "\ud83d\udfe9", "\ud83d\udfe9", "\ud83d\udfe9", "\ud83d\udfe9", "\ud83c\udf32", "\ud83c\udf32", "\ud83d\udfe9", "\ud83c\udf32", "\ud83c\udf32", "\ud83d\udfe9", "\ud83c\udf32", "\ud83d\udfe9", "\ud83c\udf32", "\ud83d\udfe9", "\ud83d\udfe9", "\ud83d\udfe9", "\ud83d\udfe9", "\ud83d\udfe9", "\ud83d\udfe9", "\ud83d\udfe9", "\ud83d\udfe9", "\ud83d\udfe9", "\ud83d\udfeb"], ["\ud83d\udfeb", "\ud83c\udf32", "\ud83c\udf32", "\ud83d\udfe9", "\ud83d\udfe9", "\ud83c\udf32", "\ud83c\udf32", "\ud83c\udf32", "\ud83d\udfe9", "\ud83d\udfe9", "\ud83c\udf32", "\ud83c\udf32", "\ud83c\udf32", "\ud83c\udf32", "\ud83d\udfe9", "\ud83d\udfe9", "\ud83d\udfe9", "\ud83c\udf32", "\ud83d\udfe9", "\ud83c\udf32", "\ud83d\udfe9", "\ud83c\udf32", "\ud83d\udfe9", "\ud83d\udfe9", "\ud83d\udfe9", "\ud83d\udfe9", "\ud83d\udfe9", "\ud83d\udfe9", "\ud83d\udfe9", "\ud83d\udfeb"], ["\ud83d\udfeb", "\ud83d\udfe9", "\ud83d\udfe9", "\ud83d\udfe9", "\ud83c\udf32", "\ud83c\udf32", "\ud83c\udf32", "\ud83d\udfe6", "\ud83d\udfe9", "\ud83c\udf32", "\ud83c\udf32", "\ud83c\udf32", "\ud83c\udf32", "\ud83c\udf32", "\ud83c\udf32", "\ud83d\udfe9", "\ud83c\udf32", "\ud83d\udfe9", "\ud83d\udfe9", "\ud83c\udf32", "\ud83d\udfe9", "\ud83d\udfe9", "\ud83d\udfe9", "\ud83d\udfe9", "\ud83d\udfe9", "\ud83d\udfe9", "\ud83d\udfe9", "\ud83d\udfe9", "\ud83d\udfe9", "\ud83d\udfeb"], ["\ud83d\udfeb", "\ud83d\udfe9", "\ud83d\udfe9", "\ud83d\udfe9", "\ud83d\udfe9", "\ud83d\udfe9", "\ud83d\udfe6", "\ud83d\udfe6", "\ud83c\udf32", "\ud83c\udf32", "\ud83c\udf32", "\ud83c\udf32", "\ud83c\udf32", "\ud83c\udf32", "\ud83c\udf32", "\ud83d\udfe9", "\ud83d\udfe9", "\ud83c\udf32", "\ud83c\udf32", "\ud83c\udf32", "\ud83c\udf32", "\ud83d\udfe9", "\ud83d\udfe9", "\ud83d\udfe9", "\ud83d\udfe9", "\ud83d\udfe9", "\ud83d\udfe9", "\ud83d\udfe9", "\ud83d\udfe9", "\ud83d\udfeb"], ["\ud83d\udfeb", "\ud83d\udfe9", "\ud83d\udfe9", "\ud83d\udfe9", "\ud83d\udfe9", "\ud83d\udfe9", "\ud83d\udfe6", "\ud83d\udfe9", "\ud83c\udf32", "\ud83c\udf32", "\ud83c\udf32", "\ud83c\udf32", "\ud83c\udf32", "\ud83d\udfe9", "\ud83d\udfe6", "\ud83d\udfe9", "\ud83d\udfe9", "\ud83c\udf32", "\ud83c\udf32", "\ud83c\udf32", "\ud83c\udf32", "\ud83d\udfe9", "\ud83d\udfe9", "\ud83d\udfe9", "\ud83d\udfe9", "\ud83c\udf32", "\ud83d\udfe9", "\ud83d\udfe9", "\ud83d\udfe9", "\ud83d\udfeb"], ["\ud83d\udfeb", "\ud83d\udfe9", "\ud83d\udfe9", "\ud83d\udfe9", "\ud83c\udf32", "\ud83d\udfe6", "\ud83d\udfe6", "\ud83d\udfe9", "\ud83d\udfe9", "\ud83c\udf32", "\ud83d\udfe9", "\ud83c\udf32", "\ud83d\udfe9", "\ud83d\udfe9", "\ud83d\udfe6", "\ud83d\udfe9", "\ud83c\udf32", "\ud83c\udf32", "\ud83c\udf32", "\ud83c\udf32", "\ud83c\udf32", "\ud83d\udfe9", "\ud83d\udfe9", "\ud83c\udf32", "\ud83d\udfe9", "\ud83d\udfe9", "\ud83d\udfe9", "\ud83d\udfe9", "\ud83d\udfe9", "\ud83d\udfeb"], ["\ud83d\udfeb", "\ud83d\udfe9", "\ud83d\udfe9", "\ud83c\udf32", "\ud83c\udf32", "\ud83c\udf32", "\ud83d\udfe6", "\ud83d\udfe9", "\ud83d\udfe9", "\ud83d\udfe9", "\ud83c\udf32", "\ud83d\udfe9", "\ud83c\udf32", "\ud83d\udfe9", "\ud83d\udfe6", "\ud83d\udfe6", "\ud83d\udfe6", "\ud83d\udfe9", "\ud83c\udf32", "\ud83d\udfe9", "\ud83c\udf32", "\ud83d\udfe9", "\ud83d\udfe9", "\ud83c\udf32", "\ud83d\udfe9", "\ud83d\udfe9", "\ud83d\udfe9", "\ud83d\udfe9", "\ud83d\udfe9", "\ud83d\udfeb"], ["\ud83d\udfeb", "\ud83d\udfe9", "\ud83d\udfe6", "\ud83d\udfe6", "\ud83c\udf32", "\ud83c\udf32", "\ud83c\udf32", "\ud83c\udf32", "\ud83d\udd25", "\ud83d\udfe9", "\ud83c\udf32", "\ud83d\udfe9", "\ud83d\udfe9", "\ud83d\udfe9", "\ud83d\udfe9", "\ud83d\udfe9", "\ud83d\udfe6", "\ud83d\udfe9", "\ud83d\udfe9", "\ud83d\udfe9", "\ud83c\udf32", "\ud83c\udf32", "\ud83c\udf32", "\ud83d\udfe9", "\ud83d\udfe9", "\ud83d\udfe9", "\ud83d\udfe9", "\ud83d\udfe9", "\ud83d\udfe9", "\ud83d\udfeb"], ["\ud83d\udfeb", "\ud83d\udfeb", "\ud83d\udfeb", "\ud83d\udfeb", "\ud83d\udfeb", "\ud83d\udfeb", "\ud83d\udfeb", "\ud83d\udfeb", "\ud83d\udfeb", "\ud83d\udfeb", "\ud83d\udfeb", "\ud83d\udfeb", "\ud83d\udfeb", "\ud83d\udfeb", "\ud83d\udfeb", "\ud83d\udfeb", "\ud83d\udfeb", "\ud83d\udfeb", "\ud83d\udfeb", "\ud83d\udfeb", "\ud83d\udfeb", "\ud83d\udfeb", "\ud83d\udfeb", "\ud83d\udfeb", "\ud83d\udfeb", "\ud83d\udfeb", "\ud83d\udfeb", "\ud83d\udfeb", "\ud83d\udfeb", "\ud83d\udfeb"]]}}